logcc/__init__.py
logcc/color_formatter.py
logcc/logcc.py
logcc/netboy_handler.py
logcc/pony_sqlite_handler.py
logcc/util/__init__.py
logcc/util/table.py
logcc/web/__init__.py
logcc/web/clusterize.css
logcc/web/clusterize.min.js
logcc/web/index.html
logcc/web/server.py
logcc-2018.2.3.dist-info/DESCRIPTION.rst
logcc-2018.2.3.dist-info/METADATA
logcc-2018.2.3.dist-info/RECORD
logcc-2018.2.3.dist-info/WHEEL
logcc-2018.2.3.dist-info/metadata.json
logcc-2018.2.3.dist-info/top_level.txt
