Metadata-Version: 2.0
Name: logcc
Version: 2018.2.3
Summary: log with colors
Home-page: https://github.com/pingf/logcc.git
Author: Jesse MENG
Author-email: pingf0@gmail.com
License: BSD
Platform: any
Classifier: Intended Audience :: Developers
Classifier: License :: OSI Approved :: BSD License
Classifier: Operating System :: OS Independent
Classifier: Programming Language :: Python
Classifier: Topic :: Software Development :: Libraries :: Python Modules
Requires-Dist: termcc
Requires-Dist: loader
Requires-Dist: aiohttp
Requires-Dist: aiofiles
Requires-Dist: websockets
Requires-Dist: pony
Requires-Dist: terminaltables
